llama_index/readers/openapi/BUILD
llama_index/readers/openapi/__init__.py
llama_index/readers/openapi/base.py
llama_index_readers_openapi-0.3.0.dist-info/METADATA
llama_index_readers_openapi-0.3.0.dist-info/WHEEL
llama_index_readers_openapi-0.3.0.dist-info/RECORD
